setman/.version
setman/__classpath__.py
setman/__init__.py
setman/__main__.py
setman/welcome.txt
setman/core/__init__.py
setman/core/setman.py
setman/core/setman_config.py
setman/core/setman_enums.py
setman/resources/sql/V0__create_tables.sql
setman/resources/sql/V1__create_triggers.sql
setman/settings/__init__.py
setman/settings/settings.py
setman/settings/settings_config.py
setman/settings/settings_entry.py
setman/settings/settings_repository.py
setman/settings/settings_service.py
hspylib_setman-0.10.43.dist-info/METADATA
hspylib_setman-0.10.43.dist-info/WHEEL
hspylib_setman-0.10.43.dist-info/top_level.txt
hspylib_setman-0.10.43.dist-info/RECORD
